perennial_sdk/__init__.py
perennial_sdk/abi/__init__.py
perennial_sdk/abi/dsu_abi.py
perennial_sdk/abi/emptyset_reserve_abi.py
perennial_sdk/abi/erc_20_abi.py
perennial_sdk/abi/keeper_factory_abi.py
perennial_sdk/abi/keeper_oracle_abi.py
perennial_sdk/abi/market_abi.py
perennial_sdk/abi/market_factory_abi.py
perennial_sdk/abi/multi_invoker_abi.py
perennial_sdk/abi/oracle_abi.py
perennial_sdk/abi/oracle_factory_abi.py
perennial_sdk/abi/pyth_oracle_abi.py
perennial_sdk/abi/usdc_abi.py
perennial_sdk/artifacts/__init__.py
perennial_sdk/artifacts/lens_abi.py
perennial_sdk/config/__init__.py
perennial_sdk/config/connection.py
perennial_sdk/constants/__init__.py
perennial_sdk/constants/color_codes.py
perennial_sdk/constants/contract_addresses.py
perennial_sdk/constants/market_addresses.py
perennial_sdk/constants/market_contracts.py
perennial_sdk/constants/market_provider_ids.py
perennial_sdk/constants/math.py
perennial_sdk/main/__init__.py
perennial_sdk/main/account/__init__.py
perennial_sdk/main/account/account_info.py
perennial_sdk/main/fees/__init__.py
perennial_sdk/main/fees/fees.py
perennial_sdk/main/graph_queries/__init__.py
perennial_sdk/main/graph_queries/order_fetcher.py
perennial_sdk/main/markets/__init__.py
perennial_sdk/main/markets/market_info.py
perennial_sdk/main/markets/snapshot_and_oracle_info.py
perennial_sdk/main/orders/__init__.py
perennial_sdk/main/orders/order_manager.py
perennial_sdk/sdk.py
perennial_sdk/utils/__init__.py
perennial_sdk/utils/calc_funding_rate_draft_two.py
perennial_sdk/utils/decoder_utils.py
perennial_sdk/utils/global_utils.py
perennial_sdk/utils/logger.py
perennial_sdk/utils/pyth_utils.py
tests/__init__.py
tests/account_info_t.py
tests/market_info_t.py
tests/test_utils.py
tests/tx_execution_t.py
perennial_sdk-0.1.5.dist-info/METADATA
perennial_sdk-0.1.5.dist-info/WHEEL
perennial_sdk-0.1.5.dist-info/RECORD
