Metadata-Version: 2.3
Name: perennial_sdk
Version: 0.1.5
Summary: An SDK to interact with the Perennial derivatives protocol.
Author: l3wi
Requires-Python: >=3.11,<4.0
Classifier: Programming Language :: Python :: 3
Classifier: Programming Language :: Python :: 3.11
Classifier: Programming Language :: Python :: 3.12
Classifier: Programming Language :: Python :: 3.13
Requires-Dist: eth-account (==0.13.2)
Requires-Dist: eth_abi (==5.1.0)
Requires-Dist: python-dotenv (==1.0.1)
Requires-Dist: requests (==2.32.3)
Requires-Dist: web3 (==7.0.0)
